topsis_vibhav_102003772/__init__.py
topsis_vibhav_102003772/__main__.py
topsis_vibhav_102003772-1.1.1.dist-info/LICENCE
topsis_vibhav_102003772-1.1.1.dist-info/METADATA
topsis_vibhav_102003772-1.1.1.dist-info/WHEEL
topsis_vibhav_102003772-1.1.1.dist-info/entry_points.txt
topsis_vibhav_102003772-1.1.1.dist-info/top_level.txt
topsis_vibhav_102003772-1.1.1.dist-info/RECORD
