Metadata-Version: 2.1
Name: topsis-vibhav-102003772
Version: 1.1.1
Summary: It finds topsis for the given data in csv file
Home-page: https://github.com/vibhav10/topsis-package
Author: Vibhav Shukla
Author-email: vibhav.1507@gmail.com
License: MIT
Platform: UNKNOWN
Classifier: License :: OSI Approved :: MIT License
Classifier: Programming Language :: Python :: 3.6
Classifier: Programming Language :: Python :: 3.7
Classifier: Programming Language :: Python :: 3.8
License-File: LICENCE
Requires-Dist: pandas
Requires-Dist: numpy
